CHANGELOG.rst
MANIFEST.in
README.rst
setup.py
kismet_rest/__init__.py
kismet_rest/alerts.py
kismet_rest/base_interface.py
kismet_rest/datasources.py
kismet_rest/devices.py
kismet_rest/exceptions.py
kismet_rest/gps.py
kismet_rest/legacy.py
kismet_rest/logger.py
kismet_rest/messages.py
kismet_rest/system.py
kismet_rest/utility.py
kismet_rest.egg-info/PKG-INFO
kismet_rest.egg-info/SOURCES.txt
kismet_rest.egg-info/dependency_links.txt
kismet_rest.egg-info/requires.txt
kismet_rest.egg-info/top_level.txt