Metadata-Version: 1.1
Name: kismet-rest
Version: 2020.5.1
Summary: Simplified Python API for the Kismet REST interface
Home-page: https://www.kismetwireless.net
Author: Mike Kershaw / Dragorn
Author-email: dragorn@kismetwireless.net
License: GPLv2
Download-URL: https://kismetwireless.net/python-kismet-rest
Keywords: kismet
Platform: UNKNOWN
Classifier: Development Status :: 5 - Production/Stable
Classifier: Intended Audience :: Developers
Classifier: Operating System :: MacOS :: MacOS X
Classifier: Operating System :: POSIX :: Linux
Classifier: Programming Language :: Python :: 2.7
Classifier: Programming Language :: Python :: 3.5
Classifier: Programming Language :: Python :: 3.6
Classifier: Programming Language :: Python :: 3.7
Classifier: Topic :: Security
Classifier: License :: OSI Approved :: GNU General Public License v2 (GPLv2)
